gsocketpool
tests
