Metadata-Version: 1.1
Name: gsocketpool
Version: 0.1.4
Summary: A simple connection pool for gevent
Home-page: http://github.com/studio-ousia/gsocketpool
Author: Studio Ousia
Author-email: admin@ousia.jp
License: Copyright 2013 Studio Ousia
